wanga/__init__.py
wanga/common.py
wanga/function.py
wanga/runtime.py
wanga/models/__init__.py
wanga/models/messages.py
wanga/models/model.py
wanga/models/openai.py
wanga/schema/__init__.py
wanga/schema/extractor.py
wanga/schema/extractor_fns.py
wanga/schema/jsonschema.py
wanga/schema/normalize.py
wanga/schema/schema.py
wanga/schema/utils.py
wanga/templates/__init__.py
wanga/templates/common.py
wanga-0.4.0.dist-info/METADATA
wanga-0.4.0.dist-info/WHEEL
wanga-0.4.0.dist-info/licenses/LICENSE
wanga-0.4.0.dist-info/RECORD
